[
  {
    "connectionId": "c1453274964263",
    "id": "ds1453348202848",
    "metadata": [
      {
        "format": "",
        "id": "RP_PA",
        "label": "RP_PA",
        "lookup": null,
        "type": "double"
      },
      {
        "format": "",
        "id": "OSC_C_PA",
        "label": "OSC_C_PA",
        "lookup": null,
        "type": "double"
      },
      {
        "format": "",
        "id": "GP_MIS",
        "label": "GP_MIS",
        "lookup": null,
        "type": "double"
      },
      {
        "format": "",
        "id": "GD_FIRE",
        "label": "GD_FIRE",
        "lookup": null,
        "type": "double"
      },
      {
        "format": "",
        "id": "UPR_C_FIRE",
        "label": "UPR_C_FIRE",
        "lookup": null,
        "type": "double"
      },
      {
        "format": "",
        "id": "OSC_C_FIRE",
        "label": "OSC_C_FIRE",
        "lookup": null,
        "type": "double"
      },
      {
        "format": "",
        "id": "GO_CAR",
        "label": "GO_CAR",
        "lookup": null,
        "type": "double"
      },
      {
        "format": "",
        "id": "GP_LIA",
        "label": "GP_LIA",
        "lookup": null,
        "type": "double"
      },
      {
        "format": "",
        "id": "ILEP_TOT",
        "label": "ILEP_TOT",
        "lookup": null,
        "type": "double"
      },
      {
        "format": "",
        "id": "GP_FIRE",
        "label": "GP_FIRE",
        "lookup": null,
        "type": "double"
      },
      {
        "format": "",
        "id": "ILEP_FIRE",
        "label": "ILEP_FIRE",
        "lookup": null,
        "type": "double"
      },
      {
        "format": "",
        "id": "GO_HULL",
        "label": "GO_HULL",
        "lookup": null,
        "type": "double"
      },
      {
        "format": "",
        "id": "UR_MIS",
        "label": "UR_MIS",
        "lookup": null,
        "type": "double"
      },
      {
        "format": "",
        "id": "XOL_FIRE",
        "label": "XOL_FIRE",
        "lookup": null,
        "type": "double"
      },
      {
        "format": "",
        "id": "GC_FIRE",
        "label": "GC_FIRE",
        "lookup": null,
        "type": "double"
      },
      {
        "format": "",
        "id": "GP_PA",
        "label": "GP_PA",
        "lookup": null,
        "type": "double"
      },
      {
        "format": "",
        "id": "XOL_ENG",
        "label": "XOL_ENG",
        "lookup": null,
        "type": "double"
      },
      {
        "format": "",
        "id": "UR_PA",
        "label": "UR_PA",
        "lookup": null,
        "type": "double"
      },
      {
        "format": "",
        "id": "GO_FIRE",
        "label": "GO_FIRE",
        "lookup": null,
        "type": "double"
      },
      {
        "format": "",
        "id": "CO_FIRE",
        "label": "CO_FIRE",
        "lookup": null,
        "type": "double"
      },
      {
        "format": "",
        "id": "UR_FIRE",
        "label": "UR_FIRE",
        "lookup": null,
        "type": "double"
      },
      {
        "format": "",
        "id": "OSC_C_CAR",
        "label": "OSC_C_CAR",
        "lookup": null,
        "type": "double"
      },
      {
        "format": "",
        "id": "RC_HULL",
        "label": "RC_HULL",
        "lookup": null,
        "type": "double"
      },
      {
        "format": "",
        "id": "ILEP_MIS",
        "label": "ILEP_MIS",
        "lookup": null,
        "type": "double"
      },
      {
        "format": "",
        "id": "IBNR_MTV",
        "label": "IBNR_MTV",
        "lookup": null,
        "type": "double"
      },
      {
        "format": "",
        "id": "GC_CAR",
        "label": "GC_CAR",
        "lookup": null,
        "type": "double"
      },
      {
        "format": "",
        "id": "RO_HULL",
        "label": "RO_HULL",
        "lookup": null,
        "type": "double"
      },
      {
        "format": "",
        "id": "UR_HULL",
        "label": "UR_HULL",
        "lookup": null,
        "type": "double"
      },
      {
        "format": "",
        "id": "IL_ENG",
        "label": "IL_ENG",
        "lookup": null,
        "type": "double"
      },
      {
        "format": "",
        "id": "GO_LIA",
        "label": "GO_LIA",
        "lookup": null,
        "type": "double"
      },
      {
        "format": "",
        "id": "RP_ENG",
        "label": "RP_ENG",
        "lookup": null,
        "type": "double"
      },
      {
        "format": "",
        "id": "UPR_C_TOT",
        "label": "UPR_C_TOT",
        "lookup": null,
        "type": "double"
      },
      {
        "format": "",
        "id": "PROD_CODE",
        "label": "PROD_CODE",
        "lookup": null,
        "type": "string"
      },
      {
        "format": "",
        "id": "RO_FIRE",
        "label": "RO_FIRE",
        "lookup": null,
        "type": "double"
      },
      {
        "format": "",
        "id": "UPR_P_MTV",
        "label": "UPR_P_MTV",
        "lookup": null,
        "type": "double"
      },
      {
        "format": "",
        "id": "RC_MTV",
        "label": "RC_MTV",
        "lookup": null,
        "type": "double"
      },
      {
        "format": "",
        "id": "GC_HULL",
        "label": "GC_HULL",
        "lookup": null,
        "type": "double"
      },
      {
        "format": "",
        "id": "RC_TOT",
        "label": "RC_TOT",
        "lookup": null,
        "type": "double"
      },
      {
        "format": "",
        "id": "RGO_TOT",
        "label": "RGO_TOT",
        "lookup": null,
        "type": "double"
      },
      {
        "format": "",
        "id": "GC_MTV",
        "label": "GC_MTV",
        "lookup": null,
        "type": "double"
      },
      {
        "format": "",
        "id": "GO_MTV",
        "label": "GO_MTV",
        "lookup": null,
        "type": "double"
      },
      {
        "format": "",
        "id": "RGO_LIA",
        "label": "RGO_LIA",
        "lookup": null,
        "type": "double"
      },
      {
        "format": "",
        "id": "GC_PA",
        "label": "GC_PA",
        "lookup": null,
        "type": "double"
      },
      {
        "format": "",
        "id": "OSC_P_MIS",
        "label": "OSC_P_MIS",
        "lookup": null,
        "type": "double"
      },
      {
        "format": "",
        "id": "RP_MIS",
        "label": "RP_MIS",
        "lookup": null,
        "type": "double"
      },
      {
        "format": "",
        "id": "RP_TOT",
        "label": "RP_TOT",
        "lookup": null,
        "type": "double"
      },
      {
        "format": "",
        "id": "OSC_P_FIRE",
        "label": "OSC_P_FIRE",
        "lookup": null,
        "type": "double"
      },
      {
        "format": "",
        "id": "RP_MTV",
        "label": "RP_MTV",
        "lookup": null,
        "type": "double"
      },
      {
        "format": "",
        "id": "IBNR_CAR",
        "label": "IBNR_CAR",
        "lookup": null,
        "type": "double"
      },
      {
        "format": "",
        "id": "XOL_HULL",
        "label": "XOL_HULL",
        "lookup": null,
        "type": "double"
      },
      {
        "format": "",
        "id": "GC_ENG",
        "label": "GC_ENG",
        "lookup": null,
        "type": "double"
      },
      {
        "format": "",
        "id": "GP_TOT",
        "label": "GP_TOT",
        "lookup": null,
        "type": "double"
      },
      {
        "format": "",
        "id": "GP_MTV",
        "label": "GP_MTV",
        "lookup": null,
        "type": "double"
      },
      {
        "format": "",
        "id": "RGO_MTV",
        "label": "RGO_MTV",
        "lookup": null,
        "type": "double"
      },
      {
        "format": "",
        "id": "IL_HULL",
        "label": "IL_HULL",
        "lookup": null,
        "type": "double"
      },
      {
        "format": "",
        "id": "XOL_PA",
        "label": "XOL_PA",
        "lookup": null,
        "type": "double"
      },
      {
        "format": "",
        "id": "GD_MIS",
        "label": "GD_MIS",
        "lookup": null,
        "type": "double"
      },
      {
        "format": "",
        "id": "GPD_FIRE",
        "label": "GPD_FIRE",
        "lookup": null,
        "type": "double"
      },
      {
        "format": "",
        "id": "UPR_P_HULL",
        "label": "UPR_P_HULL",
        "lookup": null,
        "type": "double"
      },
      {
        "format": "",
        "id": "CO_LIA",
        "label": "CO_LIA",
        "lookup": null,
        "type": "double"
      },
      {
        "format": "",
        "id": "GPD_TOT",
        "label": "GPD_TOT",
        "lookup": null,
        "type": "double"
      },
      {
        "format": "",
        "id": "GO_MIS",
        "label": "GO_MIS",
        "lookup": null,
        "type": "double"
      },
      {
        "format": "",
        "id": "RO_MIS",
        "label": "RO_MIS",
        "lookup": null,
        "type": "double"
      },
      {
        "format": "",
        "id": "CO_MIS",
        "label": "CO_MIS",
        "lookup": null,
        "type": "double"
      },
      {
        "format": "",
        "id": "PROD_CODE1",
        "label": "PROD_CODE1",
        "lookup": null,
        "type": "string"
      },
      {
        "format": "",
        "id": "UR_MTV",
        "label": "UR_MTV",
        "lookup": null,
        "type": "double"
      },
      {
        "format": "",
        "id": "GP_HULL",
        "label": "GP_HULL",
        "lookup": null,
        "type": "double"
      },
      {
        "format": "",
        "id": "RP_LIA",
        "label": "RP_LIA",
        "lookup": null,
        "type": "double"
      },
      {
        "format": "",
        "id": "OSC_C_MIS",
        "label": "OSC_C_MIS",
        "lookup": null,
        "type": "double"
      },
      {
        "format": "",
        "id": "IL_TOT",
        "label": "IL_TOT",
        "lookup": null,
        "type": "double"
      },
      {
        "format": "",
        "id": "CL_NAME",
        "label": "CL_NAME",
        "lookup": null,
        "type": "string"
      },
      {
        "format": "",
        "id": "XOL_CAR",
        "label": "XOL_CAR",
        "lookup": null,
        "type": "double"
      },
      {
        "format": "",
        "id": "OSC_C_ENG",
        "label": "OSC_C_ENG",
        "lookup": null,
        "type": "double"
      },
      {
        "format": "",
        "id": "GC_MIS",
        "label": "GC_MIS",
        "lookup": null,
        "type": "double"
      },
      {
        "format": "",
        "id": "EP_TOT",
        "label": "EP_TOT",
        "lookup": null,
        "type": "double"
      },
      {
        "format": "",
        "id": "UPR_P_CAR",
        "label": "UPR_P_CAR",
        "lookup": null,
        "type": "double"
      },
      {
        "format": "",
        "id": "GD_HULL",
        "label": "GD_HULL",
        "lookup": null,
        "type": "double"
      },
      {
        "format": "",
        "id": "RC_LIA",
        "label": "RC_LIA",
        "lookup": null,
        "type": "double"
      },
      {
        "format": "",
        "id": "IL_PA",
        "label": "IL_PA",
        "lookup": null,
        "type": "double"
      },
      {
        "format": "",
        "id": "IBNR_FIRE",
        "label": "IBNR_FIRE",
        "lookup": null,
        "type": "double"
      },
      {
        "format": "",
        "id": "EP_MTV",
        "label": "EP_MTV",
        "lookup": null,
        "type": "double"
      },
      {
        "format": "",
        "id": "RO_MTV",
        "label": "RO_MTV",
        "lookup": null,
        "type": "double"
      },
      {
        "format": "",
        "id": "RO_CAR",
        "label": "RO_CAR",
        "lookup": null,
        "type": "double"
      },
      {
        "format": "",
        "id": "IBNR_PA",
        "label": "IBNR_PA",
        "lookup": null,
        "type": "double"
      },
      {
        "format": "",
        "id": "CO_TOT",
        "label": "CO_TOT",
        "lookup": null,
        "type": "double"
      },
      {
        "format": "",
        "id": "OSC_C_MTV",
        "label": "OSC_C_MTV",
        "lookup": null,
        "type": "double"
      },
      {
        "format": "",
        "id": "ILEP_CAR",
        "label": "ILEP_CAR",
        "lookup": null,
        "type": "double"
      },
      {
        "format": "",
        "id": "OSC_P_HULL",
        "label": "OSC_P_HULL",
        "lookup": null,
        "type": "double"
      },
      {
        "format": "",
        "id": "GD_ENG",
        "label": "GD_ENG",
        "lookup": null,
        "type": "double"
      },
      {
        "format": "",
        "id": "OSC_P_ENG",
        "label": "OSC_P_ENG",
        "lookup": null,
        "type": "double"
      },
      {
        "format": "",
        "id": "GPD_ENG",
        "label": "GPD_ENG",
        "lookup": null,
        "type": "double"
      },
      {
        "format": "",
        "id": "RC_FIRE",
        "label": "RC_FIRE",
        "lookup": null,
        "type": "double"
      },
      {
        "format": "",
        "id": "RC_CAR",
        "label": "RC_CAR",
        "lookup": null,
        "type": "double"
      },
      {
        "format": "",
        "id": "UPR_C_HULL",
        "label": "UPR_C_HULL",
        "lookup": null,
        "type": "double"
      },
      {
        "format": "",
        "id": "IBNR_HULL",
        "label": "IBNR_HULL",
        "lookup": null,
        "type": "double"
      },
      {
        "format": "",
        "id": "OSC_C_LIA",
        "label": "OSC_C_LIA",
        "lookup": null,
        "type": "double"
      },
      {
        "format": "",
        "id": "GP_ENG",
        "label": "GP_ENG",
        "lookup": null,
        "type": "double"
      },
      {
        "format": "",
        "id": "UPR_P_ENG",
        "label": "UPR_P_ENG",
        "lookup": null,
        "type": "double"
      },
      {
        "format": "",
        "id": "UPR_C_PA",
        "label": "UPR_C_PA",
        "lookup": null,
        "type": "double"
      },
      {
        "format": "",
        "id": "GD_TOT",
        "label": "GD_TOT",
        "lookup": null,
        "type": "double"
      },
      {
        "format": "",
        "id": "UPR_P_TOT",
        "label": "UPR_P_TOT",
        "lookup": null,
        "type": "double"
      },
      {
        "format": "",
        "id": "IBNR_ENG",
        "label": "IBNR_ENG",
        "lookup": null,
        "type": "double"
      },
      {
        "format": "",
        "id": "RGO_ENG",
        "label": "RGO_ENG",
        "lookup": null,
        "type": "double"
      },
      {
        "format": "",
        "id": "GPD_MIS",
        "label": "GPD_MIS",
        "lookup": null,
        "type": "double"
      },
      {
        "format": "",
        "id": "CL_TYPE",
        "label": "CL_TYPE",
        "lookup": null,
        "type": "string"
      },
      {
        "format": "",
        "id": "CL_PREFIX",
        "label": "CL_PREFIX",
        "lookup": null,
        "type": "string"
      },
      {
        "format": "",
        "id": "RGO_FIRE",
        "label": "RGO_FIRE",
        "lookup": null,
        "type": "double"
      },
      {
        "format": "",
        "id": "UR_CAR",
        "label": "UR_CAR",
        "lookup": null,
        "type": "double"
      },
      {
        "format": "",
        "id": "IL_LIA",
        "label": "IL_LIA",
        "lookup": null,
        "type": "double"
      },
      {
        "format": "",
        "id": "UPR_P_MIS",
        "label": "UPR_P_MIS",
        "lookup": null,
        "type": "double"
      },
      {
        "format": "",
        "id": "OSC_C_TOT",
        "label": "OSC_C_TOT",
        "lookup": null,
        "type": "double"
      },
      {
        "format": "",
        "id": "RO_ENG",
        "label": "RO_ENG",
        "lookup": null,
        "type": "double"
      },
      {
        "format": "",
        "id": "RGO_MIS",
        "label": "RGO_MIS",
        "lookup": null,
        "type": "double"
      },
      {
        "format": "",
        "id": "IL_MTV",
        "label": "IL_MTV",
        "lookup": null,
        "type": "double"
      },
      {
        "format": "",
        "id": "OSC_C_HULL",
        "label": "OSC_C_HULL",
        "lookup": null,
        "type": "double"
      },
      {
        "format": "",
        "id": "ILEP_HULL",
        "label": "ILEP_HULL",
        "lookup": null,
        "type": "double"
      },
      {
        "format": "",
        "id": "UPR_P_LIA",
        "label": "UPR_P_LIA",
        "lookup": null,
        "type": "double"
      },
      {
        "format": "",
        "id": "ILEP_LIA",
        "label": "ILEP_LIA",
        "lookup": null,
        "type": "double"
      },
      {
        "format": "",
        "id": "RC_PA",
        "label": "RC_PA",
        "lookup": null,
        "type": "double"
      },
      {
        "format": "",
        "id": "GO_PA",
        "label": "GO_PA",
        "lookup": null,
        "type": "double"
      },
      {
        "format": "",
        "id": "IL_MIS",
        "label": "IL_MIS",
        "lookup": null,
        "type": "double"
      },
      {
        "format": "",
        "id": "EP_FIRE",
        "label": "EP_FIRE",
        "lookup": null,
        "type": "double"
      },
      {
        "format": "",
        "id": "XOL_MTV",
        "label": "XOL_MTV",
        "lookup": null,
        "type": "double"
      },
      {
        "format": "",
        "id": "UPR_C_MTV",
        "label": "UPR_C_MTV",
        "lookup": null,
        "type": "double"
      },
      {
        "format": "",
        "id": "RGO_CAR",
        "label": "RGO_CAR",
        "lookup": null,
        "type": "double"
      },
      {
        "format": "",
        "id": "CO_CAR",
        "label": "CO_CAR",
        "lookup": null,
        "type": "double"
      },
      {
        "format": "",
        "id": "UR_LIA",
        "label": "UR_LIA",
        "lookup": null,
        "type": "double"
      },
      {
        "format": "",
        "id": "OSC_P_PA",
        "label": "OSC_P_PA",
        "lookup": null,
        "type": "double"
      },
      {
        "format": "",
        "id": "EP_MIS",
        "label": "EP_MIS",
        "lookup": null,
        "type": "double"
      },
      {
        "format": "",
        "id": "GD_MTV",
        "label": "GD_MTV",
        "lookup": null,
        "type": "double"
      },
      {
        "format": "",
        "id": "EP_CAR",
        "label": "EP_CAR",
        "lookup": null,
        "type": "double"
      },
      {
        "format": "",
        "id": "RP_HULL",
        "label": "RP_HULL",
        "lookup": null,
        "type": "double"
      },
      {
        "format": "",
        "id": "EP_HULL",
        "label": "EP_HULL",
        "lookup": null,
        "type": "double"
      },
      {
        "format": "",
        "id": "UPR_C_LIA",
        "label": "UPR_C_LIA",
        "lookup": null,
        "type": "double"
      },
      {
        "format": "",
        "id": "EP_ENG",
        "label": "EP_ENG",
        "lookup": null,
        "type": "double"
      },
      {
        "format": "",
        "id": "UR_TOT",
        "label": "UR_TOT",
        "lookup": null,
        "type": "double"
      },
      {
        "format": "",
        "id": "IBNR_MIS",
        "label": "IBNR_MIS",
        "lookup": null,
        "type": "double"
      },
      {
        "format": "",
        "id": "ILEP_MTV",
        "label": "ILEP_MTV",
        "lookup": null,
        "type": "double"
      },
      {
        "format": "",
        "id": "GPD_LIA",
        "label": "GPD_LIA",
        "lookup": null,
        "type": "double"
      },
      {
        "format": "",
        "id": "RC_ENG",
        "label": "RC_ENG",
        "lookup": null,
        "type": "double"
      },
      {
        "format": "",
        "id": "UR_ENG",
        "label": "UR_ENG",
        "lookup": null,
        "type": "double"
      },
      {
        "format": "",
        "id": "CO_PA",
        "label": "CO_PA",
        "lookup": null,
        "type": "double"
      },
      {
        "format": "",
        "id": "RO_TOT",
        "label": "RO_TOT",
        "lookup": null,
        "type": "double"
      },
      {
        "format": "",
        "id": "UPR_C_CAR",
        "label": "UPR_C_CAR",
        "lookup": null,
        "type": "double"
      },
      {
        "format": "",
        "id": "OSC_P_CAR",
        "label": "OSC_P_CAR",
        "lookup": null,
        "type": "double"
      },
      {
        "format": "",
        "id": "ILEP_ENG",
        "label": "ILEP_ENG",
        "lookup": null,
        "type": "double"
      },
      {
        "format": "",
        "id": "CO_ENG",
        "label": "CO_ENG",
        "lookup": null,
        "type": "double"
      },
      {
        "format": "",
        "id": "RO_PA",
        "label": "RO_PA",
        "lookup": null,
        "type": "double"
      },
      {
        "format": "",
        "id": "RO_LIA",
        "label": "RO_LIA",
        "lookup": null,
        "type": "double"
      },
      {
        "format": "",
        "id": "UPR_C_MIS",
        "label": "UPR_C_MIS",
        "lookup": null,
        "type": "double"
      },
      {
        "format": "",
        "id": "XOL_TOT",
        "label": "XOL_TOT",
        "lookup": null,
        "type": "double"
      },
      {
        "format": "",
        "id": "OSC_P_MTV",
        "label": "OSC_P_MTV",
        "lookup": null,
        "type": "double"
      },
      {
        "format": "",
        "id": "GP_CAR",
        "label": "GP_CAR",
        "lookup": null,
        "type": "double"
      },
      {
        "format": "",
        "id": "GPD_CAR",
        "label": "GPD_CAR",
        "lookup": null,
        "type": "double"
      },
      {
        "format": "",
        "id": "GPD_HULL",
        "label": "GPD_HULL",
        "lookup": null,
        "type": "double"
      },
      {
        "format": "",
        "id": "XOL_LIA",
        "label": "XOL_LIA",
        "lookup": null,
        "type": "double"
      },
      {
        "format": "",
        "id": "ILEP_PA",
        "label": "ILEP_PA",
        "lookup": null,
        "type": "double"
      },
      {
        "format": "",
        "id": "_id",
        "label": "_id",
        "lookup": null,
        "type": "string"
      },
      {
        "format": "",
        "id": "GPD_MTV",
        "label": "GPD_MTV",
        "lookup": null,
        "type": "double"
      },
      {
        "format": "",
        "id": "UPR_C_ENG",
        "label": "UPR_C_ENG",
        "lookup": null,
        "type": "double"
      },
      {
        "format": "",
        "id": "GO_ENG",
        "label": "GO_ENG",
        "lookup": null,
        "type": "double"
      },
      {
        "format": "",
        "id": "UPR_P_PA",
        "label": "UPR_P_PA",
        "lookup": null,
        "type": "double"
      },
      {
        "format": "",
        "id": "GD_CAR",
        "label": "GD_CAR",
        "lookup": null,
        "type": "double"
      },
      {
        "format": "",
        "id": "OSC_P_LIA",
        "label": "OSC_P_LIA",
        "lookup": null,
        "type": "double"
      },
      {
        "format": "",
        "id": "XOL_MIS",
        "label": "XOL_MIS",
        "lookup": null,
        "type": "double"
      },
      {
        "format": "",
        "id": "GO_TOT",
        "label": "GO_TOT",
        "lookup": null,
        "type": "double"
      },
      {
        "format": "",
        "id": "CO_MTV",
        "label": "CO_MTV",
        "lookup": null,
        "type": "double"
      },
      {
        "format": "",
        "id": "IL_CAR",
        "label": "IL_CAR",
        "lookup": null,
        "type": "double"
      },
      {
        "format": "",
        "id": "CO_HULL",
        "label": "CO_HULL",
        "lookup": null,
        "type": "double"
      },
      {
        "format": "",
        "id": "EP_LIA",
        "label": "EP_LIA",
        "lookup": null,
        "type": "double"
      },
      {
        "format": "",
        "id": "IBNR_LIA",
        "label": "IBNR_LIA",
        "lookup": null,
        "type": "double"
      },
      {
        "format": "",
        "id": "RP_FIRE",
        "label": "RP_FIRE",
        "lookup": null,
        "type": "double"
      },
      {
        "format": "",
        "id": "RP_CAR",
        "label": "RP_CAR",
        "lookup": null,
        "type": "double"
      },
      {
        "format": "",
        "id": "RGO_PA",
        "label": "RGO_PA",
        "lookup": null,
        "type": "double"
      },
      {
        "format": "",
        "id": "IBNR_TOT",
        "label": "IBNR_TOT",
        "lookup": null,
        "type": "double"
      },
      {
        "format": "",
        "id": "CLIENT_COD",
        "label": "CLIENT_COD",
        "lookup": null,
        "type": "string"
      },
      {
        "format": "",
        "id": "RGO_HULL",
        "label": "RGO_HULL",
        "lookup": null,
        "type": "double"
      },
      {
        "format": "",
        "id": "GC_LIA",
        "label": "GC_LIA",
        "lookup": null,
        "type": "double"
      },
      {
        "format": "",
        "id": "RC_MIS",
        "label": "RC_MIS",
        "lookup": null,
        "type": "double"
      },
      {
        "format": "",
        "id": "EP_PA",
        "label": "EP_PA",
        "lookup": null,
        "type": "double"
      },
      {
        "format": "",
        "id": "GC_TOT",
        "label": "GC_TOT",
        "lookup": null,
        "type": "double"
      },
      {
        "format": "",
        "id": "OSC_P_TOT",
        "label": "OSC_P_TOT",
        "lookup": null,
        "type": "double"
      },
      {
        "format": "",
        "id": "UPR_P_FIRE",
        "label": "UPR_P_FIRE",
        "lookup": null,
        "type": "double"
      },
      {
        "format": "",
        "id": "IL_FIRE",
        "label": "IL_FIRE",
        "lookup": null,
        "type": "double"
      },
      {
        "format": "",
        "id": "GD_LIA",
        "label": "GD_LIA",
        "lookup": null,
        "type": "double"
      },
      {
        "format": "",
        "id": "GD_PA",
        "label": "GD_PA",
        "lookup": null,
        "type": "double"
      },
      {
        "format": "",
        "id": "GPD_PA",
        "label": "GPD_PA",
        "lookup": null,
        "type": "double"
      },
      {
        "format": "",
        "id": "CreatedDate",
        "label": "CreatedDate",
        "lookup": null,
        "type": "string"
      }
    ],
    "name": "adsfasdfasdfsadf",
    "query": "Select(name).From(test)"
  }
]